temprl_mcp_client/__init__.py
temprl_mcp_client/cli.py
temprl_mcp_client/client.py
temprl_mcp_client/db.py
temprl_mcp_client/setup_postgres.py
temprl_mcp_client/utils.py
temprl_mcp_client/providers/__init__.py
temprl_mcp_client/providers/anthropic.py
temprl_mcp_client/providers/lmstudio.py
temprl_mcp_client/providers/ollama.py
temprl_mcp_client/providers/openai.py
temprl_mcp_client-0.1.7.dist-info/METADATA
temprl_mcp_client-0.1.7.dist-info/WHEEL
temprl_mcp_client-0.1.7.dist-info/entry_points.txt
temprl_mcp_client-0.1.7.dist-info/top_level.txt
temprl_mcp_client-0.1.7.dist-info/RECORD
