Metadata-Version: 2.4
Name: temprl-mcp-client
Version: 0.1.7
Summary: A Python client for temporal reasoning and learning using Model Context Protocol (MCP) servers
Author: Temprl Labs Team
License: MIT
Classifier: Programming Language :: Python :: 3
Classifier: License :: OSI Approved :: MIT License
Classifier: Operating System :: OS Independent
Requires-Python: >=3.8
Requires-Dist: openai
Requires-Dist: mcp[cli]
Requires-Dist: python-dotenv
Requires-Dist: anthropic
Requires-Dist: ollama
Requires-Dist: jsonschema
Provides-Extra: dev
Requires-Dist: pytest; extra == "dev"
Requires-Dist: pytest-asyncio; extra == "dev"
Requires-Dist: pytest-mock; extra == "dev"
Requires-Dist: uv; extra == "dev"
Provides-Extra: demo
Requires-Dist: mcp-server-sqlite; extra == "demo"
